MANIFEST.in
README.rst
ciao.py
setup.py
ciao.egg-info/PKG-INFO
ciao.egg-info/SOURCES.txt
ciao.egg-info/dependency_links.txt
ciao.egg-info/requires.txt
ciao.egg-info/top_level.txt