Metadata-Version: 1.1
Name: ciao
Version: 0.1.0
Summary: Michael Corleone says ...
Home-page: https://github.com/bninja/ciao
Author: mikey
Author-email: mikey@corleone.it
License: BSD
Platform: any
Classifier: Intended Audience :: Developers
Classifier: License :: OSI Approved :: BSD License
Classifier: Operating System :: OS Independent
Classifier: Programming Language :: Python
Classifier: Topic :: Internet :: WWW/HTTP :: Dynamic Content
Classifier: Topic :: Software Development :: Libraries :: Python Modules
